{
    "personalInfo": {
        "icon": "👤",
        "title": "个人信息",
        "items": [
            "姓名：三理Mit3uri",
            "种族：人类",
            "生日：8月9日",
            "身长：166cm",
            "职业：梦境研究院（预转正）",
            "粉丝牌：锂电池",
            "应援色：#f482fd",
            "Tag：#三理的充电站",
            "代表物：🕶️"
        ]
    },
    "likesAndDislikes": {
        "icon": "💖",
        "title": "喜欢和不喜欢",
        "likes": {
            "title": "喜欢",
            "items": [
                "*唱歌*",
                "收集餐具",
                "吃肉",
                "做咖啡",
                "玩游戏",
                "酒",
                "听歌",
                "猫",
                "马克杯（厚实的）"
            ]
        },
        "dislikes": {
            "title": "不喜欢",
            "items": [
                "飞蛾",
                "*胡萝卜*",
                "DDL",
                "恐怖游戏",
                "零度可乐",
                "虫子（颜色密度高的）"
            ]
        }
    },
    "games": {
        "icon": "🎮",
        "title": "游戏",
        "items": [
            "艾尔登法环",
            "黑魂系列",
            "小猫咪大城市",
            "迷失（Stray）",
            "幻兽帕鲁",
            "饥荒",
            "揍击派对",
            "猛兽派对",
            "无畏契约",
            "英雄联盟"
        ]
    },
    "music": {
        "icon": "🎵",
        "title": "音乐",
        "items": [
            "流行",
            "R&B",
            "摇滚",
            "Citypop"
        ]
    }
} 